Primos_Rayco/__init__.py
Primos_Rayco-1.0.dist-info/LICENSE
Primos_Rayco-1.0.dist-info/METADATA
Primos_Rayco-1.0.dist-info/WHEEL
Primos_Rayco-1.0.dist-info/top_level.txt
Primos_Rayco-1.0.dist-info/RECORD
