Metadata-Version: 2.1
Name: Primos-Rayco
Version: 1.0
Summary: Sistema para calcular números primos
Home-page: UNKNOWN
Author: Rayco Fonseca Mendez
Author-email: rayco910409@gmail.com
License: GNU GPLv3
Keywords: numeros primos
Platform: UNKNOWN
Classifier: Development Status :: 4 - Beta
Classifier: Environment :: Console
Classifier: Intended Audience :: Developers
Classifier: Topic :: Utilities
Classifier: License :: OSI Approved :: GNU General Public License v3 (GPLv3)
Classifier: Programming Language :: Python :: 3
Classifier: Operating System :: OS Independent
License-File: LICENSE
